WardleyCrewAPI/__init__.py
WardleyCrewAPI/api_client.py
WardleyCrewAPI/configuration.py
WardleyCrewAPI/exceptions.py
WardleyCrewAPI/model_utils.py
WardleyCrewAPI/rest.py
WardleyCrewAPI/api/__init__.py
WardleyCrewAPI/api/conversions_api.py
WardleyCrewAPI/api/open_wardley_maps_api.py
WardleyCrewAPI/api/tools_api.py
WardleyCrewAPI/api/wardley_maps_online_api.py
WardleyCrewAPI/apis/__init__.py
WardleyCrewAPI/model/__init__.py
WardleyCrewAPI/model/component_request.py
WardleyCrewAPI/model/http_validation_error.py
WardleyCrewAPI/model/map_id_request.py
WardleyCrewAPI/model/map_text_and_warnings.py
WardleyCrewAPI/model/owm_text_request.py
WardleyCrewAPI/model/search_component_request.py
WardleyCrewAPI/model/text_request.py
WardleyCrewAPI/model/validation_error.py
WardleyCrewAPI/models/__init__.py
Wardley_API_Python_SDK-0.8.1.dist-info/METADATA
Wardley_API_Python_SDK-0.8.1.dist-info/WHEEL
Wardley_API_Python_SDK-0.8.1.dist-info/top_level.txt
Wardley_API_Python_SDK-0.8.1.dist-info/RECORD
