Metadata-Version: 2.1
Name: Wardley_API_Python_SDK
Version: 0.8.1
Summary: Wardley Mapping Crew API
Home-page: https://github.com/tractorjuice/Wardley_API_Python_SDK
Author: OpenAPI Generator community
Author-email: team@openapitools.org
Keywords: OpenAPI,OpenAPI-Generator,Wardley Mapping Crew API
Requires-Python: >=3.6
Requires-Dist: urllib3 >=1.25.3
Requires-Dist: python-dateutil
